datacleanbot/__init__.py
datacleanbot/dataclean.py
datacleanbot/bayesian/__init__.py
datacleanbot/bayesian/explain.py
datacleanbot/bayesian/utils.py
datacleanbot/bayesian/visualize.py
datacleanbot/bayesian/bin/__init__.py
datacleanbot/bayesian/bin/abda.py
datacleanbot/bayesian/bin/collect_mv_results.py
datacleanbot/bayesian/bin/collect_results.py
datacleanbot/bayesian/bin/collect_results_synth.py
datacleanbot/bayesian/bin/exp_gen_masks.py
datacleanbot/bayesian/bin/exp_gen_synth_data.py
datacleanbot/bayesian/bin/exp_learn_hspn_inductive.py
datacleanbot/bayesian/bin/exp_learn_hspn_islv.py
datacleanbot/bayesian/bin/exp_learn_hspn_synth.py
datacleanbot/bayesian/bin/exp_learn_mspn_islv.py
datacleanbot/bayesian/bin/exp_lvstd_islv_data.py
datacleanbot/bayesian/bin/exp_lvstd_synth.py
datacleanbot/bayesian/bin/gen_collect_results_mspn.py
datacleanbot/bayesian/bin/gen_synth_data.py
datacleanbot/bayesian/bin/islv_data_hspn.py
datacleanbot/bayesian/bin/lvstd.py
datacleanbot/bayesian/bin/lvstd_exp_gen.py
datacleanbot/bayesian/bin/mspn_data_to_islv.py
datacleanbot/bayesian/bin/mspn_model.py
datacleanbot/bayesian/bin/pre_process_islv_dataset.py
datacleanbot/bayesian/data/__init__.py
datacleanbot/bayesian/spn/__init__.py
datacleanbot/bayesian/spn/algorithms/Inference.py
datacleanbot/bayesian/spn/algorithms/LearningWrappers.py
datacleanbot/bayesian/spn/algorithms/Marginalization.py
datacleanbot/bayesian/spn/algorithms/Posteriors.py
datacleanbot/bayesian/spn/algorithms/Pruning.py
datacleanbot/bayesian/spn/algorithms/Sampling.py
datacleanbot/bayesian/spn/algorithms/Statistics.py
datacleanbot/bayesian/spn/algorithms/StructureLearning.py
datacleanbot/bayesian/spn/algorithms/Validity.py
datacleanbot/bayesian/spn/algorithms/__init__.py
datacleanbot/bayesian/spn/algorithms/splitting/Base.py
datacleanbot/bayesian/spn/algorithms/splitting/Clustering.py
datacleanbot/bayesian/spn/algorithms/splitting/RDC.py
datacleanbot/bayesian/spn/algorithms/splitting/Random.py
datacleanbot-0.91.dist-info/LICENSE.txt
datacleanbot-0.91.dist-info/METADATA
datacleanbot-0.91.dist-info/WHEEL
datacleanbot-0.91.dist-info/top_level.txt
datacleanbot-0.91.dist-info/RECORD
