Metadata-Version: 2.1
Name: datacleanbot
Version: 0.91
Summary: automated data cleaning tool
Home-page: https://github.com/Ji-Zhang/datacleanbot
Author: Ji Zhang
Author-email: 
License: UNKNOWN
Platform: UNKNOWN
Classifier: Programming Language :: Python :: 3
Classifier: License :: OSI Approved :: MIT License
Requires-Dist: numpy (>=1.14.2)
Requires-Dist: pandas (<=0.23.1,>=0.19.0)
Requires-Dist: scikit-learn (>=0.23.2)
Requires-Dist: scipy (>=1.2.1)
Requires-Dist: seaborn (>=0.8)
Requires-Dist: matplotlib (>=2.2.2)
Requires-Dist: missingno (==0.4.1)
Requires-Dist: openml (>=0.9.0)
Requires-Dist: fancyimpute (==0.5.5)
